setup.cfg
setup.py
ArduinoKeywords.egg-info/PKG-INFO
ArduinoKeywords.egg-info/SOURCES.txt
ArduinoKeywords.egg-info/dependency_links.txt
ArduinoKeywords.egg-info/requires.txt
ArduinoKeywords.egg-info/top_level.txt
arduinokeywords/__init__.py
arduinokeywords/arduinokeywords.py
arduinokeywords/version.py
bin/arduino-keywords