Metadata-Version: 1.0
Name: ArduinoKeywords
Version: 1.0.4
Summary: A script for automatically generating a keywords.txt file for Arduino libraries
Home-page: https://github.com/r89m/arduino-keywords
Author: Richard Miles
Author-email: pypi@fast-chat.co.uk
License: UNKNOWN
Platform: UNKNOWN
